<?xml version="1.0" encoding="UTF-8"?>
<!DOCTYPE aspectran PUBLIC "-//ASPECTRAN//DTD Aspectran Configuration 7.0//EN"
        "http://aspectran.github.io/dtd/aspectran-7.dtd">
<aspectran>

    <description>
        Defines code used for simple purposes.
    </description>

    <!-- Frequently used code bundles-->
    <environment>
        <properties>
            <item name="staticCodes" type="map">
                <entry name="languages">%{languages}</entry>
                <entry name="categories">%{categories}</entry>
                <entry name="creditCardTypes">%{creditCardTypes}</entry>
            </item>
        </properties>
    </environment>

    <environment>
        <properties>
            <item name="languages" type="map">
                <entry name="english">English</entry>
                <entry name="german">German</entry>
                <entry name="french">French</entry>
                <entry name="korean">Korean</entry>
                <entry name="japanese">Japanese</entry>
            </item>
            <item name="categories" type="map">
                <entry name="FISH">Fish</entry>
                <entry name="DOGS">Dogs</entry>
                <entry name="REPTILES">Reptiles</entry>
                <entry name="CATS">Cats</entry>
                <entry name="BIRDS">Birds</entry>
            </item>
            <item name="creditCardTypes" type="map">
                <entry name="Visa">Visa</entry>
                <entry name="MasterCard">MasterCard</entry>
                <entry name="American Express">American Express</entry>
            </item>
        </properties>
    </environment>

</aspectran>